{
    "id": "04ee49ad-9bbc-41c2-a3d5-16fc669e3de1",
    "type": "Feature",
    "geometry": {
        "type": "Point",
        "coordinates": [
            -73.9405917684788,
            40.728178574620564
        ]
    },
    "properties": {
        "title": "Repair EV chargers at Greenpoint",
        "description": "Repair EV chargers at Greenpoint\n",
        "vendor": "vendor@example.com",
        "site": "Greenpoint",
        "status": "Paused",
        "createdAt": "2025-07-16T16:41:33.529392",
        "geofence_center": [
            40.728178574620564,
            -73.9405917684788
        ],
        "geofence_radius": 500,
        "logs": [
            {
                "timestamp": "2025-07-16T16:41:33.529402",
                "user": "admin",
                "action": "Activity created."
            },
            {
                "timestamp": "2025-07-16T16:41:59.312750",
                "user": "admin",
                "action": "Work Started"
            },
            {
                "timestamp": "2025-07-16T16:45:36.092547",
                "user": "System",
                "action": "Periodic location check."
            },
            {
                "timestamp": "2025-07-16T16:45:43.996922",
                "user": "admin",
                "action": "Work Paused"
            },
            {
                "timestamp": "2025-07-16T16:45:58.612052",
                "user": "admin",
                "action": "Work Resumed"
            },
            {
                "timestamp": "2025-07-16T19:27:27.711353",
                "user": "System",
                "action": "Periodic location check."
            },
            {
                "timestamp": "2025-07-16T19:27:37.719306",
                "user": "admin",
                "action": "Work Paused"
            },
            {
                "timestamp": "2025-07-16T19:30:14.775527",
                "user": "admin",
                "action": "Comment: teat"
            }
        ],
        "location_trail": [
            {
                "timestamp": "2025-07-16T16:41:59.312761",
                "coordinates": [
                    -73.94057090296938,
                    40.72825406264576
                ]
            },
            {
                "timestamp": "2025-07-16T16:45:36.092557",
                "coordinates": [
                    -73.94057090296938,
                    40.72825406264576
                ]
            },
            {
                "timestamp": "2025-07-16T16:45:58.612086",
                "coordinates": [
                    -73.94057090296938,
                    40.72825406264576
                ]
            },
            {
                "timestamp": "2025-07-16T19:27:27.711360",
                "coordinates": [
                    -73.9300922,
                    40.7210837
                ]
            }
        ]
    }
}